Metadata-Version: 2.1
Name: adikfraction
Version: 0.0.1
Summary: Fraction operation by Adisak Karnbanjong
Home-page: https://github.com/kadisak/adikfraction
Download-URL: https://github.com/kadisak/adikfraction/archive/v0.0.1.zip
Author: Adisak Karnbanjong
Author-email: kadisak@gmail.com
License: MIT
Keywords: Fraction,Mathematics,Adisak,Karnbanjong
Classifier: Development Status :: 3 - Alpha
Classifier: Intended Audience :: Education
Classifier: Topic :: Utilities
Classifier: License :: OSI Approved :: MIT License
Classifier: Programming Language :: Python :: 3
Classifier: Programming Language :: Python :: 3.4
Classifier: Programming Language :: Python :: 3.5
Classifier: Programming Language :: Python :: 3.6
Classifier: Programming Language :: Python :: 3.7
Classifier: Programming Language :: Python :: 3.8
Classifier: Programming Language :: Python :: 3.9
Classifier: Programming Language :: Python :: 3.10
License-File: LICENSE.txt
